{
  "analysis_parameters": {
    "confidence_thresholds": {
      "high_confidence": 0.85,
      "medium_confidence": 0.70,
      "low_confidence": 0.55,
      "minimum_confidence": 0.40,
      "consensus_threshold": 0.75,
      "override_threshold": 0.90
    },
    "technical_indicators": {
      "rsi": {
        "period": 14,
        "overbought": 70,
        "oversold": 30,
        "weight": 0.15
      },
      "macd": {
        "fast_period": 12,
        "slow_period": 26,
        "signal_period": 9,
        "weight": 0.20
      },
      "bollinger_bands": {
        "period": 20,
        "std_dev": 2,
        "weight": 0.15
      },
      "moving_averages": {
        "short_ma": 20,
        "medium_ma": 50,
        "long_ma": 200,
        "weight": 0.25
      },
      "volume_analysis": {
        "volume_ma_period": 20,
        "volume_spike_threshold": 2.0,
        "weight": 0.10
      },
      "momentum": {
        "period": 10,
        "weight": 0.15
      }
    },
    "analysis_weights": {
      "technical_analysis": 0.30,
      "fundamental_analysis": 0.25,
      "sentiment_analysis": 0.20,
      "smart_money_tracking": 0.15,
      "government_contracts": 0.10
    },
    "alert_thresholds": {
      "price_change_percent": 5.0,
      "volume_spike_multiplier": 3.0,
      "sentiment_change": 0.3,
      "smart_money_activity": 0.7,
      "technical_breakout": 0.8,
      "fundamental_change": 0.6
    },
    "risk_parameters": {
      "max_position_size": 0.15,
      "max_sector_allocation": 0.40,
      "var_confidence_level": 0.05,
      "stress_test_scenarios": 5,
      "correlation_threshold": 0.70,
      "volatility_lookback_days": 252,
      "beta_calculation_period": 252
    },
    "portfolio_optimization": {
      "rebalancing_threshold": 0.05,
      "minimum_trade_size": 100,
      "transaction_cost_basis_points": 5,
      "cash_buffer_percent": 0.05,
      "max_turnover_monthly": 0.20,
      "optimization_frequency_days": 30
    },
    "scoring_parameters": {
      "ai_score_weight": 0.25,
      "growth_score_weight": 0.20,
      "value_score_weight": 0.15,
      "momentum_score_weight": 0.15,
      "quality_score_weight": 0.15,
      "esg_score_weight": 0.10
    },
    "analysis_timeframes": {
      "short_term_days": 30,
      "medium_term_days": 90,
      "long_term_days": 365,
      "trend_analysis_days": 252,
      "seasonal_analysis_years": 3
    },
    "sentiment_analysis": {
      "news_weight": 0.40,
      "social_media_weight": 0.35,
      "analyst_ratings_weight": 0.25,
      "sentiment_decay_days": 7,
      "minimum_sources": 3,
      "credibility_threshold": 0.6
    }
  },
  "thresholds": {
    "data_quality": {
      "minimum_data_points": 30,
      "minimum_history_length": 50,
      "minimum_returns_sample": 100,
      "minimum_volume_data": 20,
      "minimum_news_articles": 3,
      "minimum_social_mentions": 5,
      "data_freshness_hours": 24,
      "cache_validity_hours": 6
    },
    "analysis_thresholds": {
      "high_anomaly_count": 3,
      "medium_anomaly_count": 2,
      "low_anomaly_count": 1,
      "high_risk_position_count": 3,
      "cache_freshness_ratio": 0.5,
      "consensus_factor_minimum": 4,
      "strong_signal_threshold": 0.8,
      "weak_signal_threshold": 0.3
    },
    "performance_limits": {
      "max_alert_log_entries": 1000,
      "max_authentication_attempts": 30,
      "max_api_retries": 3,
      "max_concurrent_requests": 10,
      "max_memory_usage_mb": 2048,
      "max_processing_time_seconds": 300,
      "subscriber_count_threshold": 50000
    },
    "portfolio_limits": {
      "max_single_position_percent": 15,
      "min_portfolio_positions": 5,
      "max_portfolio_positions": 50,
      "max_sector_allocation_percent": 40,
      "min_cash_allocation_percent": 5,
      "max_cash_allocation_percent": 20,
      "rebalancing_threshold_percent": 5,
      "concentration_risk_threshold": 0.7
    },
    "risk_management": {
      "var_confidence_levels": [0.01, 0.05, 0.10],
      "stress_test_thresholds": {
        "severe_loss": -0.25,
        "major_loss": -0.20,
        "moderate_loss": -0.15,
        "minor_loss": -0.10
      },
      "correlation_thresholds": {
        "high_correlation": 0.8,
        "moderate_correlation": 0.6,
        "low_correlation": 0.3
      },
      "volatility_thresholds": {
        "high_volatility": 0.30,
        "moderate_volatility": 0.20,
        "low_volatility": 0.10
      }
    },
    "market_conditions": {
      "volume_spike_multipliers": {
        "extreme": 5.0,
        "high": 3.0,
        "moderate": 2.0,
        "normal": 1.0
      },
      "price_movement_thresholds": {
        "significant": 0.10,
        "moderate": 0.05,
        "minor": 0.02,
        "negligible": 0.01
      },
      "market_cap_boundaries": {
        "mega_cap": 200000000000,
        "large_cap": 10000000000,
        "mid_cap": 2000000000,
        "small_cap": 300000000,
        "micro_cap": 50000000
      }
    },
    "social_sentiment": {
      "mention_volume_thresholds": {
        "viral": 100,
        "high": 50,
        "moderate": 20,
        "low": 10,
        "minimal": 5
      },
      "sentiment_score_ranges": {
        "very_bullish": 0.8,
        "bullish": 0.6,
        "neutral": 0.4,
        "bearish": 0.2,
        "very_bearish": 0.0
      },
      "influence_thresholds": {
        "high_influence": 0.8,
        "moderate_influence": 0.6,
        "low_influence": 0.3
      }
    },
    "news_analysis": {
      "sentiment_confidence_threshold": 0.7,
      "article_relevance_threshold": 0.6,
      "source_credibility_threshold": 0.8,
      "freshness_hours": 24,
      "max_articles_per_symbol": 20
    },
    "technical_analysis": {
      "trend_strength_thresholds": {
        "strong_uptrend": 0.8,
        "moderate_uptrend": 0.6,
        "sideways": 0.4,
        "moderate_downtrend": 0.2,
        "strong_downtrend": 0.0
      },
      "support_resistance_tolerance": 0.02,
      "breakout_confirmation_percent": 0.03,
      "pattern_reliability_threshold": 0.7
    },
    "government_contracts": {
      "significant_contract_value": 50000000,
      "major_contract_value": 100000000,
      "mega_contract_value": 500000000,
      "tracking_threshold": 10000000,
      "ai_keyword_relevance": 0.6
    },
    "esg_scoring": {
      "minimum_acceptable_score": 6.0,
      "good_score_threshold": 7.0,
      "excellent_score_threshold": 8.5,
      "score_change_alert_threshold": 1.0,
      "compliance_threshold": 0.70
    },
    "system_health": {
      "cpu_usage_warning": 80,
      "memory_usage_warning": 85,
      "disk_usage_warning": 90,
      "api_error_rate_threshold": 0.05,
      "response_time_threshold_ms": 5000,
      "uptime_requirement_percent": 99.5
    },
    "alert_priorities": {
      "critical": {
        "portfolio_loss_percent": 10,
        "system_failure": true,
        "security_breach": true
      },
      "high": {
        "portfolio_loss_percent": 5,
        "significant_price_movement": 0.15,
        "large_contract_award": 100000000
      },
      "medium": {
        "portfolio_loss_percent": 2,
        "moderate_price_movement": 0.10,
        "medium_contract_award": 50000000
      },
      "low": {
        "portfolio_loss_percent": 1,
        "minor_price_movement": 0.05,
        "small_contract_award": 10000000
      }
    }
  }
}
